gpyConsole/__init__.py
gpyConsole/abc.py
gpyConsole/cog.py
gpyConsole/console.py
gpyConsole/console_commands.py
gpyConsole/context.py
gpyConsole/converters.py
gpyConsole/core.py
gpyConsole/errors.py
gpyConsole/events.py
gpy_console-0.2.3.dist-info/METADATA
gpy_console-0.2.3.dist-info/WHEEL
gpy_console-0.2.3.dist-info/top_level.txt
gpy_console-0.2.3.dist-info/RECORD
