Metadata-Version: 2.1
Name: gpy-console
Version: 0.2.3
Summary: Execute your bot's commands from the console!
Home-page: https://github.com/EcoNuker/guilded.py-console
Author: YumYummity
License: MIT
Classifier: Programming Language :: Python :: 3.7
Requires-Dist: google-re2
Requires-Dist: typing
Requires-Dist: aioconsole
Provides-Extra: gil.py
Requires-Dist: gil.py ; extra == 'gil.py'
Provides-Extra: guilded.py
Requires-Dist: guilded.py ; extra == 'guilded.py'
